sinapsis_darts_forecasting/src/sinapsis_darts_forecasting/__init__.py
sinapsis_darts_forecasting/src/sinapsis_darts_forecasting/helpers/__init__.py
sinapsis_darts_forecasting/src/sinapsis_darts_forecasting/helpers/tags.py
sinapsis_darts_forecasting/src/sinapsis_darts_forecasting/templates/__init__.py
sinapsis_darts_forecasting/src/sinapsis_darts_forecasting/templates/time_series_dataframe_loader.py
sinapsis_darts_forecasting/src/sinapsis_darts_forecasting/templates/time_series_model.py
sinapsis_darts_forecasting/src/sinapsis_darts_forecasting/templates/time_series_preprocessing.py
sinapsis_time_series-0.1.7.dist-info/licenses/LICENSE
sinapsis_time_series-0.1.7.dist-info/METADATA
sinapsis_time_series-0.1.7.dist-info/WHEEL
sinapsis_time_series-0.1.7.dist-info/top_level.txt
sinapsis_time_series-0.1.7.dist-info/RECORD
