Metadata-Version: 2.4
Name: sinapsis-time-series
Version: 0.1.7
Summary: Module that contains different packages to perform time-series-related operations through Sinapsis templates.
Author-email: SinapsisAI <dev@sinapsis.tech>
Project-URL: Homepage, https://sinapsis.tech
Project-URL: Documentation, https://docs.sinapsis.tech/docs
Project-URL: Tutorials, https://docs.sinapsis.tech/tutorials
Project-URL: Repository, https://github.com/Sinapsis-AI/sinapsis-time-series.git
Requires-Python: >=3.10
License-File: LICENSE
Requires-Dist: sinapsis>=0.1.1
Provides-Extra: webapp-gradio
Requires-Dist: matplotlib>=3.9.2; extra == "webapp-gradio"
Requires-Dist: sinapsis[webapp]>=0.2.7; extra == "webapp-gradio"
Provides-Extra: all
Requires-Dist: sinapsis-darts-forecasting[all]; extra == "all"
Requires-Dist: sinapsis-time-series[webapp-gradio]; extra == "all"
Dynamic: license-file
